pynng/exceptions.py
pynng/_nng.abi3.so
pynng/_version.py
pynng/__init__.py
pynng/options.py
pynng/nng.py
pynng/_aio.py
pynng/tls.py
pynng/sockaddr.py
pynng-0.8.1.dist-info/LICENSE.txt
pynng-0.8.1.dist-info/RECORD
pynng-0.8.1.dist-info/METADATA
pynng-0.8.1.dist-info/WHEEL
pynng-0.8.1.dist-info/top_level.txt
