Metadata-Version: 2.1
Name: pynng
Version: 0.8.1
Summary: Networking made simply using nng
Author-email: Cody Piersall <cody.piersall@gmail.com>
License: The MIT License
Project-URL: Homepage, https://github.com/codypiersall/pynng
Project-URL: Source, https://github.com/codypiersall/pynng
Project-URL: Documentation, https://pynng.readthedocs.io/en/latest/
Keywords: networking,nng,nanomsg,zmq,messaging,message,trio,asyncio
Classifier: Development Status :: 3 - Alpha
Classifier: Framework :: AsyncIO
Classifier: Framework :: Trio
Classifier: License :: OSI Approved :: MIT License
Classifier: Operating System :: OS Independent
Classifier: Programming Language :: Python :: 3 :: Only
Classifier: Programming Language :: Python :: 3.6
Classifier: Programming Language :: Python :: 3.7
Classifier: Programming Language :: Python :: 3.8
Classifier: Programming Language :: Python :: 3.9
Classifier: Programming Language :: Python :: 3.10
Classifier: Topic :: Software Development :: Libraries
Classifier: Topic :: System :: Networking
License-File: LICENSE.txt
Requires-Dist: cffi
Requires-Dist: sniffio
Provides-Extra: dev
Requires-Dist: pytest ; extra == 'dev'
Requires-Dist: pytest-asyncio ; extra == 'dev'
Requires-Dist: pytest-trio ; extra == 'dev'
Requires-Dist: trio ; extra == 'dev'
Provides-Extra: docs
Requires-Dist: sphinx ; extra == 'docs'
Requires-Dist: sphinx-rtd-theme ; extra == 'docs'
Requires-Dist: sphinxcontrib-trio ; extra == 'docs'
